pylogflow/Pylogflow.py
pylogflow/__init__.py
pylogflow-0.2.0.dist-info/LICENSE
pylogflow-0.2.0.dist-info/METADATA
pylogflow-0.2.0.dist-info/WHEEL
pylogflow-0.2.0.dist-info/top_level.txt
pylogflow-0.2.0.dist-info/RECORD
