Metadata-Version: 2.1
Name: pylogflow
Version: 0.2.0
Summary: Dialogflow Webhook utility package
Home-page: https://github.com/JacobMaldonado/pylogflow.git
Author: Jacob Maldonado
Author-email: jacobmaldonado99@gmail.com
License: UNKNOWN
Platform: UNKNOWN
Classifier: Programming Language :: Python :: 3
Classifier: License :: OSI Approved :: MIT License
Classifier: Operating System :: OS Independent
